{
  "hollywood": {
    "posted_ids": [
      "316042",
      "339530",
      "86835",
      "609681",
      "250734",
      "403100",
      "256962",
      "376504",
      "338676",
      "223485",
      "367732",
      "325173",
      "286565",
      "321741",
      "354857",
      "308504",
      "333674",
      "308369",
      "277355",
      "291270",
      "376651",
      "250124",
      "271674",
      "258363",
      "524047",
      "324857",
      "318256",
      "146301",
      "458293",
      "264337",
      "319075",
      "283698",
      "353686",
      "333348",
      "395883",
      "1198994",
      "321697",
      "655511",
      "290751",
      "326215",
      "1292662",
      "326359",
      "414977",
      "295886",
      "299536",
      "266396",
      "283227",
      "351901",
      "257344",
      "359790",
      "76600",
      "336560",
      "214756",
      "256961",
      "309503",
      "302429",
      "288036",
      "188222",
      "293970",
      "361050",
      "321528",
      "323027",
      "360055",
      "325813",
      "301875",
      "292040",
      "308639",
      "301351",
      "320588",
      "256924",
      "256591",
      "293660",
      "362583",
      "350802",
      "244117",
      "362057",
      "567609",
      "243938",
      "355111",
      "248574",
      "269149",
      "57876",
      "290764",
      "266294",
      "296100",
      "308032",
      "301228",
      "433536",
      "294254",
      "254302",
      "228066",
      "345323",
      "263109",
      "744275",
      "1084242",
      "306745",
      "239573",
      "340684",
      "273610",
      "354743",
      "274167",
      "369069",
      "342927",
      "382517",
      "322766",
      "335866",
      "502356",
      "83533",
      "410605",
      "297556",
      "343807",
      "238713",
      "299534",
      "326284",
      "300803",
      "347847",
      "664767",
      "1173559",
      "245168",
      "167810",
      "346808",
      "1226863",
      "245698",
      "324807",
      "228973",
      "301846",
      "228203",
      "218784",
      "280092",
      "355338",
      "285783",
      "297291",
      "460465",
      "370835",
      "286519",
      "307663",
      "347688",
      "159824",
      "440249",
      "283235",
      "415847",
      "361743",
      "253412",
      "329829"
    ],
    "last_year": 2015,
    "last_page": 10
  },
  "bollywood": {
    "posted_ids": [
      "339795",
      "318106",
      "325389",
      "601635",
      "848116",
      "360814",
      "1160018",
      "1135873",
      "342291",
      "367189",
      "334875",
      "538858",
      "1291608",
      "799177",
      "266038",
      "358893",
      "347797",
      "363343",
      "347897",
      "352205",
      "400662",
      "556271",
      "323426",
      "357563",
      "330636",
      "784651",
      "510386",
      "432527",
      "606717",
      "316654",
      "331297",
      "312056",
      "441909",
      "363413",
      "335392",
      "374305",
      "361129",
      "376812",
      "325892",
      "314690",
      "585268",
      "352099",
      "601337",
      "1339876",
      "365497",
      "339169",
      "1446616",
      "355279",
      "599925",
      "714338",
      "330431",
      "370665",
      "1190511",
      "360817",
      "328402",
      "373016",
      "476830"
    ],
    "last_year": 2015,
    "last_page": 4
  },
  "south_indian": {
    "posted_ids": [
      "362150",
      "1118224",
      "311166",
      "759989",
      "356516",
      "280942",
      "1403735",
      "1542352",
      "365187",
      "1561687",
      "800383",
      "264038",
      "461126",
      "795104",
      "344708",
      "540468",
      "364023",
      "320910",
      "280168",
      "346667",
      "690957",
      "263471",
      "364795",
      "642889",
      "927342",
      "1068452",
      "607310",
      "456287",
      "456017",
      "595228",
      "1511417",
      "454292",
      "426614",
      "770906"
    ],
    "last_year": 2015,
    "last_page": 3
  },
  "korean": {
    "posted_ids": [
      "502235",
      "685833",
      "852370",
      "936245",
      "581528",
      "639988",
      "511642",
      "1321179",
      "955555",
      "897160",
      "838209",
      "619803",
      "698779",
      "799379",
      "1268127",
      "982843",
      "496243",
      "801604"
    ],
    "last_year": 2017,
    "last_page": 1
  },
  "japanese": {
    "posted_ids": [
      "715756",
      "976893",
      "940721",
      "504253",
      "1600672",
      "1357633",
      "1311031",
      "568160",
      "635302",
      "916224",
      "820067",
      "372058",
      "585747",
      "810693",
      "1575337",
      "1159311",
      "499191",
      "378064",
      "449574",
      "1404791",
      "452970",
      "283566"
    ],
    "last_year": 2015,
    "last_page": 1
  },
  "tv_series": {
    "posted_ids": [
      "220102",
      "276161",
      "85552",
      "125988",
      "278178",
      "37854",
      "124364",
      "224941",
      "308014",
      "94997",
      "279323",
      "76479",
      "286709",
      "246461",
      "260592",
      "296206",
      "219971",
      "299167",
      "94664",
      "277439",
      "273240",
      "278624"
    ],
    "last_year": 2026,
    "last_page": 1
  },
  "trending": {
    "posted_ids": [
      "1315772",
      "1368314",
      "1413976",
      "1430077",
      "1304313",
      "1340206",
      "1275779",
      "1318621",
      "1380291",
      "1202033",
      "1228710",
      "1439930",
      "936075",
      "1397385",
      "1280738",
      "1122573",
      "1440050",
      "1301421",
      "1477317",
      "1368881",
      "1226863",
      "969681",
      "1084244",
      "1242332",
      "1327819",
      "1633263",
      "1358005",
      "1127384",
      "931285",
      "454639",
      "614945",
      "950028",
      "1339713",
      "1318413",
      "1710008",
      "1468683",
      "1484913",
      "1170608",
      "1058424",
      "1108427",
      "1081003",
      "687163",
      "1368337",
      "1560681",
      "1390300",
      "1212763",
      "1451344",
      "1273221",
      "1083381",
      "1314481"
    ],
    "last_year": 2026,
    "last_page": 1
  }
}